dashai_test_classification_metrics_package/__init__.py
dashai_test_classification_metrics_package/accuracy.py
dashai_test_classification_metrics_package/classification_metric.py
dashai_test_classification_metrics_package/f1.py
dashai_test_classification_metrics_package/precision.py
dashai_test_classification_metrics_package/recall.py
dashai_test_classification_metrics_package-0.0.1.dist-info/METADATA
dashai_test_classification_metrics_package-0.0.1.dist-info/WHEEL
dashai_test_classification_metrics_package-0.0.1.dist-info/entry_points.txt
dashai_test_classification_metrics_package-0.0.1.dist-info/RECORD
